CHANGES.rst
LICENSE
MANIFEST.in
README.rst
setup.py
bitlyapi/__init__.py
bitlyapi/bitly.py
bitlyapi.egg-info/PKG-INFO
bitlyapi.egg-info/SOURCES.txt
bitlyapi.egg-info/dependency_links.txt
bitlyapi.egg-info/requires.txt
bitlyapi.egg-info/top_level.txt
scripts/bitly