Metadata-Version: 1.0
Name: bitlyapi
Version: 0.1.1
Summary: A thin wrapper for the bit.ly REST API
Home-page: http://github.com/hellp/bitlyapi
Author: Fabian Neumann
Author-email: fn@sturzbach.de
License: BSD
Platform: UNKNOWN
Classifier: Development Status :: 4 - Beta
Classifier: Intended Audience :: Developers
Classifier: License :: OSI Approved :: BSD License
Classifier: Programming Language :: Python
Classifier: Programming Language :: Python :: 2.5
Classifier: Programming Language :: Python :: 2.6
Classifier: Topic :: Internet :: WWW/HTTP
Classifier: Topic :: Software Development :: Libraries
Classifier: Topic :: Software Development :: Libraries :: Python Modules
